{"format":2,"version":"5.4","globals":"38c562db668a4c95c907bca7a3be0717","files":{"computer_py":{"hash":"6aa4f5e95ce128c04e6059138ab8cc90","index":{"nums":[1,47,0,0,0,0,0],"html_filename":"computer_py.html","relative_filename":"computer.py"}},"computer_test_py":{"hash":"4e0458f68ce4288b86a1f1096037e76f","index":{"nums":[1,71,0,0,0,0,0],"html_filename":"computer_test_py.html","relative_filename":"computer_test.py"}},"dice_py":{"hash":"c24c6dd80a9f9abf35965a93056aa1ae","index":{"nums":[1,10,0,0,0,0,0],"html_filename":"dice_py.html","relative_filename":"dice.py"}},"dice_test_py":{"hash":"05425f83990a53211c0a86ca69127f4a","index":{"nums":[1,16,0,0,0,0,0],"html_filename":"dice_test_py.html","relative_filename":"dice_test.py"}},"game_py":{"hash":"7a1f1c6633eab6539d603cca90ce29e1","index":{"nums":[1,129,0,0,0,0,0],"html_filename":"game_py.html","relative_filename":"game.py"}},"game_test_py":{"hash":"c503afdab4278c00da827ccd742b0d3e","index":{"nums":[1,108,0,0,0,0,0],"html_filename":"game_test_py.html","relative_filename":"game_test.py"}},"leaderboard_py":{"hash":"09666db7ed2efd13aa55ea771ceb0a39","index":{"nums":[1,51,0,0,0,0,0],"html_filename":"leaderboard_py.html","relative_filename":"leaderboard.py"}},"leaderboard_test_py":{"hash":"2cb1445e390b460a3dcba5c575564721","index":{"nums":[1,49,0,0,0,0,0],"html_filename":"leaderboard_test_py.html","relative_filename":"leaderboard_test.py"}},"player_py":{"hash":"8aae8844a1ca5b461f7a6cb04d47ae15","index":{"nums":[1,12,0,0,0,0,0],"html_filename":"player_py.html","relative_filename":"player.py"}},"player_test_py":{"hash":"ed9e2f62ceef651fd66b4f20443527ad","index":{"nums":[1,23,0,0,0,0,0],"html_filename":"player_test_py.html","relative_filename":"player_test.py"}}}}